{"name": "Ambarès-et-Lagrave", "id": 33003, "postal": "33440"}
{"name": "Ambès", "id": 33004, "postal": "33810"}
{"name": "Artigues-près-Bordeaux", "id": 33013, "postal": "33370"}
{"name": "Ayguemorte-les-Graves", "id": 33023, "postal": "33640"}
{"name": "Bassens", "id": 33032, "postal": "33530"}
{"name": "Baurech", "id": 33033, "postal": "33880"}
{"name": "Beautiran", "id": 33037, "postal": "33640"}
{"name": "Bègles", "id": 33039, "postal": "33130"}
{"name": "Beychac-et-Caillau", "id": 33049, "postal": "33750"}
{"name": "Blanquefort", "id": 33056, "postal": "33290"}
{"name": "Blésignac", "id": 33059, "postal": "33670"}
{"name": "Bonnetan", "id": 33061, "postal": "33370"}
{"name": "Bordeaux", "id": 33063, "postal": "33000"}
{"name": "Bouliac", "id": 33065, "postal": "33270"}
{"name": "Le Bouscat", "id": 33069, "postal": "33110"}
{"name": "Bruges", "id": 33075, "postal": "33520"}
{"name": "Cabanac-et-Villagrains", "id": 33077, "postal": "33650"}
{"name": "Cadaujac", "id": 33080, "postal": "33140"}
{"name": "Camarsac", "id": 33083, "postal": "33750"}
{"name": "Cambes", "id": 33084, "postal": "33880"}
{"name": "Camblanes-et-Meynac", "id": 33085, "postal": "33360"}
{"name": "Canéjan", "id": 33090, "postal": "33610"}
{"name": "Carbon-Blanc", "id": 33096, "postal": "33560"}
{"name": "Carignan-de-Bordeaux", "id": 33099, "postal": "33360"}
{"name": "Castres-Gironde", "id": 33109, "postal": "33640"}
{"name": "Cénac", "id": 33118, "postal": "33360"}
{"name": "Cenon", "id": 33119, "postal": "33150"}
{"name": "Cestas", "id": 33122, "postal": "33610"}
{"name": "Créon", "id": 33140, "postal": "33670"}
{"name": "Croignon", "id": 33141, "postal": "33750"}
{"name": "Cursan", "id": 33145, "postal": "33670"}
{"name": "Eysines", "id": 33162, "postal": "33320"}
{"name": "Fargues-Saint-Hilaire", "id": 33165, "postal": "33370"}
{"name": "Floirac", "id": 33167, "postal": "33270"}
{"name": "Gradignan", "id": 33192, "postal": "33170"}
{"name": "Le Haillan", "id": 33200, "postal": "33185"}
{"name": "Haux", "id": 33201, "postal": "33550"}
{"name": "Isle-Saint-Georges", "id": 33206, "postal": "33640"}
{"name": "La Brède", "id": 33213, "postal": "33650"}
{"name": "Latresne", "id": 33234, "postal": "33360"}
{"name": "Léognan", "id": 33238, "postal": "33850"}
{"name": "Lignan-de-Bordeaux", "id": 33245, "postal": "33360"}
{"name": "Lormont", "id": 33249, "postal": "33310"}
{"name": "Loupes", "id": 33252, "postal": "33370"}
{"name": "Ludon-Médoc", "id": 33256, "postal": "33290"}
{"name": "Macau", "id": 33262, "postal": "33460"}
{"name": "Madirac", "id": 33263, "postal": "33670"}
{"name": "Martignas-sur-Jalle", "id": 33273, "postal": "33127"}
{"name": "Martillac", "id": 33274, "postal": "33650"}
{"name": "Mérignac", "id": 33281, "postal": "33700"}
{"name": "Montussan", "id": 33293, "postal": "33450"}
{"name": "Parempuyre", "id": 33312, "postal": "33290"}
{"name": "Pessac", "id": 33318, "postal": "33600"}
{"name": "Le Pian-Médoc", "id": 33322, "postal": "33290"}
{"name": "Pompignac", "id": 33330, "postal": "33370"}
{"name": "Le Pout", "id": 33335, "postal": "33670"}
{"name": "Quinsac", "id": 33349, "postal": "33360"}
{"name": "Sadirac", "id": 33363, "postal": "33670"}
{"name": "Saint-Aubin-de-Médoc", "id": 33376, "postal": "33160"}
{"name": "Saint-Caprais-de-Bordeaux", "id": 33381, "postal": "33880"}
{"name": "Sainte-Eulalie", "id": 33397, "postal": "33560"}
{"name": "Saint-Genès-de-Lombaud", "id": 33408, "postal": "33670"}
{"name": "Saint-Jean-d'Illac", "id": 33422, "postal": "33127"}
{"name": "Saint-Léon", "id": 33431, "postal": "33670"}
{"name": "Saint-Loubès", "id": 33433, "postal": "33450"}
{"name": "Saint-Louis-de-Montferrand", "id": 33434, "postal": "33440"}
{"name": "Saint-Médard-d'Eyrans", "id": 33448, "postal": "33650"}
{"name": "Saint-Médard-en-Jalles", "id": 33449, "postal": "33160"}
{"name": "Saint-Morillon", "id": 33454, "postal": "33650"}
{"name": "Saint-Selve", "id": 33474, "postal": "33650"}
{"name": "Saint-Sulpice-et-Cameyrac", "id": 33483, "postal": "33450"}
{"name": "Saint-Vincent-de-Paul", "id": 33487, "postal": "33440"}
{"name": "Sallebœuf", "id": 33496, "postal": "33370"}
{"name": "Saucats", "id": 33501, "postal": "33650"}
{"name": "La Sauve", "id": 33505, "postal": "33670"}
{"name": "Tabanac", "id": 33518, "postal": "33550"}
{"name": "Le Taillan-Médoc", "id": 33519, "postal": "33320"}
{"name": "Talence", "id": 33522, "postal": "33400"}
{"name": "Le Tourne", "id": 33534, "postal": "33550"}
{"name": "Tresses", "id": 33535, "postal": "33370"}
{"name": "Villenave-d'Ornon", "id": 33550, "postal": "33140"}
{"name": "Yvrac", "id": 33554, "postal": "33370"}
